---
layout: post
title: [JVM]深入了解Class类及字节码
date: 2018-08-22
tags:
   - jvm
---
# Class类分析
官方文档：[参考](https://docs.oracle.com/javase/specs/jvms/se8/html/jvms-4.html)
Class类文件：
```

ClassFile {
  u4 magic; // 魔法数字，表明当前文件是.class文件，固定0xCAFEBABE 教育 u2 minor_version; // 分别为Class文件的副版本和主版本 服 u2 major_version; 务 u2 constant_pool_count; // 常量池计数 平台 cp_info constant_pool[constant_pool_count-1]; //
  u2 access_flags; // 类访问标识
  u2 this_class; // 当前类
  u2 super_class; // 父类
  u2 interfaces_count; // 实现的接口数
  u2 interfaces[interfaces_count]; // 实现接口信息
  u2 fields_count; // 字段数量
  field_info fields[fields_count]; // 包含的字段信息
  u2 methods_count; // 方法数量
  method_info methods[methods_count]; // 包含的方法信息
  u2 attributes_count; // 属性数量
  attribute_info attributes[attributes_count]; // 各种属性
}


```由以上可以发现类的结构是这样的：
  - 魔数
  - Class文件版本
  - 常量池
  - 访问标志
  - 类索引，父类索引，接口索引集合
  - 字段表集合
  - 方法表集合
  - 属性表集合
  
# 字节码解读

java语言文件：
```

public class Test1 {
	public static void main(String args) {
		int a=2;
		int b=400;
		int c = a + b;
		System.out.println(c);
	}
}



```生成的字节码：

```
/***
	 public static void main(java.lang.String);
    descriptor: (Ljava/lang/String;)V
    flags: ACC_PUBLIC, ACC_STATIC   #关键字
    Code:
      # 操作数栈的深度2
      # 本地变量表最大长度（slot为单位），64位的是2，其他是1，索引从0开始，如果是非static方法索引0代表this，后面是入参，后面是本地变量
      # 1个参数，实例方法多一个this参数
      stack=2, locals=4, args_size=1
         0: iconst_2  #常量2压栈
         1: istore_1  #出栈保存到本地变量1里面
         2: iconst_3  #常量3压栈
         3: istore_2  #出栈保存到本地变量2里面
         4: iload_1    #局部变量1压栈
         5: iload_2    #局部变量2压栈
         6: iadd        # 栈顶两个元素相加，计算结果压栈
         7: istore_3  # 出栈保存到局部变量3里面
         8: getstatic     #16                 // Field java/lang/System.out:Ljava/io/PrintStream;
        11: iload_3
        12: invokevirtual #22                 // Method java/io/PrintStream.println:(I)V
        15: return
      LineNumberTable:
        line 5: 0
        line 6: 2
        line 7: 4
        line 8: 8
        line 9: 15
      LocalVariableTable:                   //本地变更表
        Start  Length  Slot  Name   Signature
            0      16     0  args   Ljava/lang/String;
            2      14     1     a   I
            4      12     2     b   I
            8       8     3     c   I
	 **/

```以上已经对字所有解释都是注释;

## 案例一:StringBuilder与'+'的性参比较

```
public class StringAdd {
	public static void main(String[] args) {
	}

	/**
	 public static void f1();
    descriptor: ()V
    flags: ACC_PUBLIC, ACC_STATIC
    Code:
      stack=3, locals=2, args_size=0
         0: ldc           #19                 // String
         2: astore_0
         3: iconst_0
         4: istore_1
         5: goto          31
         8: new           #21                 // class java/lang/StringBuilder
        11: dup
        12: aload_0
        13: invokestatic  #23                 // Method java/lang/String.valueOf:(Ljava/lang/Object;)Ljava/lang/String;
        16: invokespecial #29                 // Method java/lang/StringBuilder."<init>":(Ljava/lang/String;)V   new StringBuilder（src）
        19: ldc           #32                 // String A
        21: invokevirtual #34                 // Method java/lang/StringBuilder.append:(Ljava/lang/String;)Ljava/lang/StringBuilder;
        24: invokevirtual #38                 // Method java/lang/StringBuilder.toString:()Ljava/lang/String;
        27: astore_0
        28: iinc          1, 1
        31: iload_1
        32: bipush        10
        34: if_icmplt     8
        37: getstatic     #42                 // Field java/lang/System.out:Ljava/io/PrintStream;
        40: aload_0
        41: invokevirtual #48                 // Method java/io/PrintStream.println:(Ljava/lang/String;)V
        44: return
	 * */
	public static void f1() {
		String src = "";
		for(int i=0;i<10;i++) {
			//每一次循环都会new一个StringBuilder
			src = src + "A";
		}
		System.out.println(src);
	}

	/**
	 *
	 *  public static void f2();
	 Code:
	 0: new           #3                  // class java/lang/StringBuilder
	 3: dup
	 4: invokespecial #4                  // Method java/lang/StringBuilder."<init>":()V
	 7: astore_0
	 8: iconst_0
	 9: istore_1
	 10: iload_1
	 11: bipush        10
	 13: if_icmpge     29
	 16: aload_0
	 17: ldc           #6                  // String A
	 19: invokevirtual #5                  // Method java/lang/StringBuilder.append:(Ljava/lang/String;)Ljava/lang/StringBuilder;
	 22: pop
	 23: iinc          1, 1
	 26: goto          10
	 29: getstatic     #8                  // Field java/lang/System.out:Ljava/io/PrintStream;
	 32: aload_0
	 33: invokevirtual #10                 // Method java/io/PrintStream.println:(Ljava/lang/Object;)V
	 36: return
	 */

	public static void f2() {
		//只要一个StringBuilder
		StringBuilder src = new StringBuilder();
		for(int i=0;i<10;i++) {
			src.append("A");
		}
		System.out.println(src);
	}


```从字节码中可以看出f1在循环中不断创建StringBuilder。所以f2>f1

## 案例二 Finally中reture的值
> 返回值是hello还是tanliu

```
	/**
	 public static java.lang.String f1();
    descriptor: ()Ljava/lang/String;
    flags: ACC_PUBLIC, ACC_STATIC
    Code:
      stack=1, locals=3, args_size=0
         0: ldc           #34                 // String hello  （加载数据）
         2: astore_0                                            //赋值
         3: aload_0												//压栈
         4: astore_2                 							//赋值（return）
         5: ldc           #36                 // String tanliu   //加载常量
         7: astore_0
         8: aload_2                                             //压栈
         9: areturn
        10: astore_1
        11: ldc           #36                 // String tanliu
        13: astore_0
        14: aload_1
        15: athrow
	 * */
	public static String f1() {
		String str = "hello";
        try{
            return str;
        }
        finally{
            str = "tanliu";
        }
	}

```
 从字节码中可以看出reture的是aload_2。已经压到栈中了。后面再修改str也是没用的了。栈中的值还是不会发生变化
